snulk/__init__.py
snulk/__main__.py
snulk/bulk_submitter.py
snulk/exceptions.py
snulk/main.py
snulk/return_field.py
snulk/submit_field.py
snulk/submit_table.py
snulk/submit_tables.py
snulk/util.py
snulk-1.0.1.dist-info/METADATA
snulk-1.0.1.dist-info/WHEEL
snulk-1.0.1.dist-info/entry_points.txt
snulk-1.0.1.dist-info/licenses/LICENSE
snulk-1.0.1.dist-info/RECORD
