Metadata-Version: 2.3
Name: SNulk
Version: 1.0.1
Summary: SNulk provides a means to submit a large number of templated records to a table on a ServiceNow instance based on provided data. The table, instance, template, and data are all customizable and intended to be modified to fit the situation.
Project-URL: Homepage, https://github.com/ServiceNow/SNulk
Project-URL: Repository, https://github.com/ServiceNow/SNulk
Author-email: "sigmund.gorski" <sigmund.gorski@servicenow.com>
Maintainer-email: "sigmund.gorski" <sigmund.gorski@servicenow.com>
License: MIT License
License-File: LICENSE
Keywords: SNulk,ServiceNow,pysnc
Classifier: Development Status :: 4 - Beta
Classifier: Intended Audience :: Developers
Classifier: License :: OSI Approved :: MIT License
Classifier: Operating System :: OS Independent
Classifier: Programming Language :: Python :: 3.11
Classifier: Programming Language :: Python :: 3.12
Requires-Python: >=3.11
Requires-Dist: jsonpickle>=3.0.3
Requires-Dist: openpyxl>=3.1.2
Requires-Dist: pandas>=2.2.0
Requires-Dist: pysnc>=1.1.5
Requires-Dist: ruamel-yaml>=0.18.6
Requires-Dist: selenium>=4.18.1
Requires-Dist: xlsxwriter>=3.2.0
